under_score/__init__.py
under_score-0.1.0.dist-info/WHEEL
under_score-0.1.0.dist-info/METADATA
under_score-0.1.0.dist-info/RECORD
